abx_plugin_htmltotext/__init__.py
abx_plugin_htmltotext/config.py
abx_plugin_htmltotext/htmltotext.py
abx_plugin_htmltotext-2024.10.28.dist-info/METADATA
abx_plugin_htmltotext-2024.10.28.dist-info/WHEEL
abx_plugin_htmltotext-2024.10.28.dist-info/entry_points.txt
abx_plugin_htmltotext-2024.10.28.dist-info/RECORD
